testpackages159/__init__.py
testpackages159-0.0.2.dist-info/METADATA
testpackages159-0.0.2.dist-info/WHEEL
testpackages159-0.0.2.dist-info/top_level.txt
testpackages159-0.0.2.dist-info/RECORD
